odoo/addons/account_payment_return_import_sepa_pain/README.rst
odoo/addons/account_payment_return_import_sepa_pain/__init__.py
odoo/addons/account_payment_return_import_sepa_pain/__manifest__.py
odoo/addons/account_payment_return_import_sepa_pain/data/payment.return.reason.csv
odoo/addons/account_payment_return_import_sepa_pain/i18n/account_payment_return_import_sepa_pain.pot
odoo/addons/account_payment_return_import_sepa_pain/i18n/de.po
odoo/addons/account_payment_return_import_sepa_pain/i18n/es.po
odoo/addons/account_payment_return_import_sepa_pain/i18n/sl.po
odoo/addons/account_payment_return_import_sepa_pain/models/__init__.py
odoo/addons/account_payment_return_import_sepa_pain/models/payment_return.py
odoo/addons/account_payment_return_import_sepa_pain/readme/CONTRIBUTORS.rst
odoo/addons/account_payment_return_import_sepa_pain/readme/DESCRIPTION.rst
odoo/addons/account_payment_return_import_sepa_pain/readme/INSTALL.rst
odoo/addons/account_payment_return_import_sepa_pain/static/description/icon.png
odoo/addons/account_payment_return_import_sepa_pain/static/description/icon.svg
odoo/addons/account_payment_return_import_sepa_pain/static/description/index.html
odoo/addons/account_payment_return_import_sepa_pain/test_files/test-sepa-unpaid.xml
odoo/addons/account_payment_return_import_sepa_pain/test_files/test-sepa-unpaid.zip
odoo/addons/account_payment_return_import_sepa_pain/tests/__init__.py
odoo/addons/account_payment_return_import_sepa_pain/tests/test_import_sepa_pain.py
odoo/addons/account_payment_return_import_sepa_pain/wizard/__init__.py
odoo/addons/account_payment_return_import_sepa_pain/wizard/pain_parser.py
odoo/addons/account_payment_return_import_sepa_pain/wizard/payment_return_import.py
odoo12_addon_account_payment_return_import_sepa_pain-12.0.1.0.1.99.dev3.dist-info/METADATA
odoo12_addon_account_payment_return_import_sepa_pain-12.0.1.0.1.99.dev3.dist-info/RECORD
odoo12_addon_account_payment_return_import_sepa_pain-12.0.1.0.1.99.dev3.dist-info/WHEEL
odoo12_addon_account_payment_return_import_sepa_pain-12.0.1.0.1.99.dev3.dist-info/top_level.txt
