Metadata-Version: 2.1
Name: odoo12-addon-account-payment-return-import-sepa-pain
Version: 12.0.1.0.1.99.dev3
Summary: Module to import SEPA Direct Debit Unpaid Report File Format PAIN.002.001.03
Home-page: https://github.com/OCA/account-payment/tree/12.0/account_payment_return_import_sepa_pain
Author: Tecnativa,Odoo Community Association (OCA)
Author-email: support@odoo-community.org
License: AGPL-3
Platform: UNKNOWN
Classifier: Programming Language :: Python
Classifier: Framework :: Odoo
Classifier: License :: OSI Approved :: GNU Affero General Public License v3
Requires-Python: >=3.5
Requires-Dist: odoo12-addon-account-payment-order
Requires-Dist: odoo12-addon-account-payment-return-import
Requires-Dist: odoo (<12.1dev,>=12.0a)
